{
  "display": {
    "icon": {
      "item": "changed_addon:syringe_with_litix_cammonia"
    },
    "title": {
      "translate": "advancements.over_dose.title"
    },
    "description": {
      "translate": "advancements.over_dose.descr"
    },
    "frame": "challenge",
    "show_toast": true,
    "announce_to_chat": true,
    "hidden": true
  },
  "criteria": {
    "over_dose": {
      "trigger": "minecraft:consume_item",
      "conditions": {
        "item": {
          "items": [
            "changed_addon:syringe_with_litix_cammonia"
          ]
        },
        "player": {
          "player": {
            "stats": [
              {
                "type": "minecraft:used",
                "stat": "changed_addon:syringe_with_litix_cammonia",
                "value": {
                  "min": 132,
                  "max": 999999
                }
              }
            ]
          }
        }
      }
    }
  },
  "parent": "changed_addon:timesthesyringewasuseadvancement_3"
}