{
  "_fv": 43,
  "_type": "achievement",
  "definition": {
    "achievementName": "Ammonia Particles",
    "achievementDescription": "You crafted Ammonia Particles congratulations",
    "achievementIcon": {
      "value": "CUSTOM:Ammoniaparticle"
    },
    "background": "Default",
    "disableDisplay": false,
    "showPopup": true,
    "announceToChat": false,
    "hideIfNotCompleted": true,
    "rewardLoot": [],
    "rewardRecipes": [],
    "rewardFunction": "No function",
    "rewardXP": 0,
    "achievementType": "task",
    "parent": {
      "value": "CUSTOM:CatlyzerAdvancement"
    },
    "triggerxml": "<xml xmlns=\"https://developers.google.com/blockly/xml\"><block type=\"custom_trigger\" x=\"28\" y=\"42\"><next><block type=\"advancement_trigger\" deletable=\"false\"></block></next></block></xml>"
  }
}